[
    {
        "key": "dbln",
        "value": "%7B%2261564727362466%22%3A%22qez5Z2aO%22%2C%22100054612486980%22%3A%22grQiqZDC%22%7D",
        "domain": "facebook.com",
        "path": "/login/device-based/",
        "hostOnly": false,
        "creation": "2024-08-22T09:37:28.580Z",
        "lastAccessed": "2024-08-22T09:37:28.581Z"
    },
    {
        "key": "datr",
        "value": "rK_FZimTG0X5_eOE5w3hK-hO",
        "domain": "facebook.com",
        "path": "/",
        "hostOnly": false,
        "creation": "2024-08-22T09:37:28.581Z",
        "lastAccessed": "2024-08-22T09:37:28.581Z"
    },
    {
        "key": "sb",
        "value": "rK_FZpZK6FCl0OL--8DvaSc3",
        "domain": "facebook.com",
        "path": "/",
        "hostOnly": false,
        "creation": "2024-08-22T09:37:28.581Z",
        "lastAccessed": "2024-08-22T09:37:28.581Z"
    },
    {
        "key": "ps_l",
        "value": "1",
        "domain": "facebook.com",
        "path": "/",
        "hostOnly": false,
        "creation": "2024-08-22T09:37:28.581Z",
        "lastAccessed": "2024-08-22T09:37:28.581Z"
    },
    {
        "key": "ps_n",
        "value": "1",
        "domain": "facebook.com",
        "path": "/",
        "hostOnly": false,
        "creation": "2024-08-22T09:37:28.581Z",
        "lastAccessed": "2024-08-22T09:37:28.581Z"
    },
    {
        "key": "vpd",
        "value": "v1%3B651x333x2.157599449157715",
        "domain": "facebook.com",
        "path": "/",
        "hostOnly": false,
        "creation": "2024-08-22T09:37:28.581Z",
        "lastAccessed": "2024-08-22T09:37:28.581Z"
    },
    {
        "key": "m_pixel_ratio",
        "value": "2.157599449157715",
        "domain": "facebook.com",
        "path": "/",
        "hostOnly": false,
        "creation": "2024-08-22T09:37:28.581Z",
        "lastAccessed": "2024-08-22T09:37:28.581Z"
    },
    {
        "key": "dpr",
        "value": "2.157599449157715",
        "domain": "facebook.com",
        "path": "/",
        "hostOnly": false,
        "creation": "2024-08-22T09:37:28.581Z",
        "lastAccessed": "2024-08-22T09:37:28.581Z"
    },
    {
        "key": "c_user",
        "value": "100054612486980",
        "domain": "facebook.com",
        "path": "/",
        "hostOnly": false,
        "creation": "2024-08-22T09:37:28.582Z",
        "lastAccessed": "2024-08-22T09:37:28.582Z"
    },
    {
        "key": "fr",
        "value": "0KPZ6RoNJnYqQajQG.AWWuTuteha-XV7NpQ5P4YsC6HXg.Bmxa-s..AAA.0.0.BmxwYl.AWVOVNmOvBI",
        "domain": "facebook.com",
        "path": "/",
        "hostOnly": false,
        "creation": "2024-08-22T09:37:28.582Z",
        "lastAccessed": "2024-08-22T09:37:28.582Z"
    },
    {
        "key": "xs",
        "value": "16%3A6iAFtg_PV0xLlw%3A2%3A1724319270%3A-1%3A16334",
        "domain": "facebook.com",
        "path": "/",
        "hostOnly": false,
        "creation": "2024-08-22T09:37:28.582Z",
        "lastAccessed": "2024-08-22T09:37:28.582Z"
    },
    {
        "key": "m_page_voice",
        "value": "100054612486980",
        "domain": "facebook.com",
        "path": "/",
        "hostOnly": false,
        "creation": "2024-08-22T09:37:28.582Z",
        "lastAccessed": "2024-08-22T09:37:28.582Z"
    },
    {
        "key": "wd",
        "value": "334x651",
        "domain": "facebook.com",
        "path": "/",
        "hostOnly": false,
        "creation": "2024-08-22T09:37:28.582Z",
        "lastAccessed": "2024-08-22T09:37:28.582Z"
    },
    {
        "key": "locale",
        "value": "hi_IN",
        "domain": "facebook.com",
        "path": "/",
        "hostOnly": false,
        "creation": "2024-08-22T09:37:28.582Z",
        "lastAccessed": "2024-08-22T09:37:28.582Z"
    },
    {
        "key": "fbl_st",
        "value": "101334999%3BT%3A28738656",
        "domain": "facebook.com",
        "path": "/",
        "hostOnly": false,
        "creation": "2024-08-22T09:37:28.582Z",
        "lastAccessed": "2024-08-22T09:37:28.582Z"
    },
    {
        "key": "wl_cbv",
        "value": "v2%3Bclient_version%3A2600%3Btimestamp%3A1724319403",
        "domain": "facebook.com",
        "path": "/",
        "hostOnly": false,
        "creation": "2024-08-22T09:37:28.582Z",
        "lastAccessed": "2024-08-22T09:37:28.582Z"
    }
]
